tap2shacl.py
ap/__init__.py
ap/ap.py
ap/shapeInfo.py
ap/statementTemplate.py
ap2shacl/__init__.py
ap2shacl/ap2shaclConverter.py
tap2ap/__init__.py
tap2ap/tap2apConverter.py
tap2shacl/__init__.py
tap2shacl/__main__.py
tap2shacl/_version.py
tap2shacl/parseArguments.py
tap2shacl/tap2shaclConverter.py
tap2shacl-1.0.0b6.dist-info/licenses/LICENSE.txt
tap2shacl-1.0.0b6.dist-info/METADATA
tap2shacl-1.0.0b6.dist-info/WHEEL
tap2shacl-1.0.0b6.dist-info/entry_points.txt
tap2shacl-1.0.0b6.dist-info/top_level.txt
tap2shacl-1.0.0b6.dist-info/RECORD
