Metadata-Version: 2.4
Name: tap2shacl
Version: 1.0.0b6
Summary: DC TAP to SHACL converter.
Author-email: Phil Barker <phil.barker@pjjk.co.uk>
License-Expression: GPL-2.0-only
Project-URL: Homepage, https://github.com/philbarker/TAP2SHACL/
Keywords: RDF,metadata application profile,SHACL
Classifier: Programming Language :: Python
Classifier: Programming Language :: Python :: 3
Classifier: Development Status :: 4 - Beta
Classifier: Intended Audience :: Developers
Classifier: Intended Audience :: Information Technology
Classifier: Natural Language :: English
Requires-Python: >=3.9
License-File: LICENSE.txt
Requires-Dist: rdflib>=7.0.0
Requires-Dist: pyyaml>=6.0.1
Requires-Dist: click>=7.1.2
Requires-Dist: pygetch>=0.1.0
Requires-Dist: dctap==0.4.5
Provides-Extra: dev
Requires-Dist: pytest>=6.2; extra == "dev"
Requires-Dist: black>=21.6b0; extra == "dev"
Requires-Dist: pytest-black>=0.3.12; extra == "dev"
Requires-Dist: pyinstaller>=5.4; extra == "dev"
Dynamic: license-file
